tapioca_google/__init__.py
tapioca_google/resource_mapping.py
tapioca_google/tapioca_google.py
tapioca_google-0.1.dist-info/DESCRIPTION.rst
tapioca_google-0.1.dist-info/METADATA
tapioca_google-0.1.dist-info/RECORD
tapioca_google-0.1.dist-info/WHEEL
tapioca_google-0.1.dist-info/metadata.json
tapioca_google-0.1.dist-info/top_level.txt
