Metadata-Version: 2.0
Name: tapioca-google
Version: 0.1
Summary: google API wrapper using tapioca
Home-page: https://github.com/lerrua/tapioca-google
Author: Igor P. Leroy
Author-email: ip.leroy@gmail.com
License: MIT
Keywords: google
Platform: UNKNOWN
Classifier: Development Status :: 5 - Production/Stable
Classifier: Intended Audience :: Developers
Classifier: License :: OSI Approved :: MIT License
Classifier: Natural Language :: English
Classifier: Programming Language :: Python :: 2
Classifier: Programming Language :: Python :: 2.7
Classifier: Programming Language :: Python :: 3
Classifier: Programming Language :: Python :: 3.1
Classifier: Programming Language :: Python :: 3.2
Classifier: Programming Language :: Python :: 3.3
Classifier: Programming Language :: Python :: 3.4
Classifier: Programming Language :: Python :: 3.5
Requires-Dist: requests-oauthlib (>=0.4.2)
Requires-Dist: tapioca-wrapper (<2)
